LICENSE
aiohcloud/__init__.py
aiohcloud/client.py
aiohcloud/enums/__init__.py
aiohcloud/enums/actions.py
aiohcloud/enums/sorting.py
aiohcloud/errors.py
aiohcloud/handlers/__init__.py
aiohcloud/handlers/abc.py
aiohcloud/handlers/actions.py
aiohcloud/handlers/datacenters.py
aiohcloud/py.typed
aiohcloud/types/__init__.py
aiohcloud/types/actions.py
aiohcloud/types/base.py
aiohcloud/types/datacenters.py
aiohcloud/types/locations.py
aiohcloud/utils.py
aiohcloud-0.0.7.dist-info/LICENSE
aiohcloud-0.0.7.dist-info/WHEEL
aiohcloud-0.0.7.dist-info/METADATA
aiohcloud-0.0.7.dist-info/RECORD
