Metadata-Version: 2.1
Name: aiohcloud
Version: 0.0.7
Summary: Asynchronous python library for Hetzner Cloud API.
Home-page: https://github.com/IHosseini083/AIOHCloud
License: GPL-3.0-only
Keywords: hcloud,wrapper,async
Author: Seyed Iliya
Author-email: pyseyed@gmail.com
Requires-Python: >=3.8,<4.0
Classifier: Intended Audience :: Developers
Classifier: License :: OSI Approved :: GNU General Public License v3 (GPLv3)
Classifier: Operating System :: OS Independent
Classifier: Programming Language :: Python :: 3
Classifier: Programming Language :: Python :: 3.8
Classifier: Programming Language :: Python :: 3.9
Classifier: Programming Language :: Python :: 3.10
Classifier: Programming Language :: Python :: 3.11
Classifier: Programming Language :: Python :: 3 :: Only
Classifier: Programming Language :: Python :: 3.10
Classifier: Programming Language :: Python :: 3.8
Classifier: Programming Language :: Python :: 3.9
Classifier: Topic :: Software Development :: Libraries :: Application Frameworks
Classifier: Topic :: Software Development :: Libraries :: Python Modules
Classifier: Typing :: Typed
Requires-Dist: attrs (>=22.2.0,<23.0.0)
Requires-Dist: httpx (>=0.23.2,<0.24.0)
Requires-Dist: typing-extensions (>=4.4.0,<5.0.0)
Project-URL: Bug Tracker, https://github.com/IHosseini083/AIOHCloud/issues
Project-URL: Repository, https://github.com/IHosseini083/AIOHCloud
